Workbook

Sheet Dashboard
A1: HAL — Executive Dashboard
A2: Comparative financial analysis vs Dassault Aviation & Lockheed Martin • live model • public data
A4: Key metrics — HAL (latest year & model output)
B6: =HAL_Data!F5 -> 33089 | D6: =HAL_Data!F11/HAL_Data!F5 -> 0.27549941 | F6: =HAL_Data!F11/HAL_Data!F13 -> 0.22211934
B9: Revenue FY26 (₹cr) | D9: Net margin | F9: ROE
B12: =POWER(HAL_Data!F5/HAL_Data!B5,1/4)-1 -> 0.076710376 | D12: =DCF_Valuation!C18 -> 2420.0354 | F12: =DCF_Valuation!C19 -> -0.43124903
B15: Revenue CAGR (5y) | D15: DCF value / share (₹) | F15: DCF upside vs price
A17: Active scenario case
B18: =Assumptions!B11 -> Base | D18: ← change on the Assumptions sheet to flex the forecast & DCF
A20: Three-company snapshot (latest year)
A21: Metric | B21: HAL | C21: Dassault | D21: Lockheed
A22: Net margin | B22: =HAL_Data!F11/HAL_Data!F5 -> 0.27549941 | C22: =Dassault_Data!F7/Dassault_Data!F5 -> 0.14291487 | D22: =Lockheed_Data!F8/Lockheed_Data!F5 -> 0.066850549
A23: Revenue CAGR (5y) | B23: =POWER(HAL_Data!F5/HAL_Data!B5,1/4)-1 -> 0.076710376 | C23: =POWER(Dassault_Data!F5/Dassault_Data!B5,1/4)-1 -> 0.0065025156 | D23: =POWER(Lockheed_Data!F5/Lockheed_Data!B5,1/4)-1 -> 0.02859593
A24: Net debt / EBITDA | B24: =(HAL_Data!F14-HAL_Data!F11)/HAL_Data!F6 -> -0.93193449 | C24: -2.5 | D24: =Lockheed_Data!F11/(Lockheed_Data!F5*Lockheed_Data!F16) -> 1.8664283
A25: EV / EBITDA | B25: =Comps!C10 -> 26.565404 | C25: =Comps!D10 -> 7.0866142 | D25: =Comps!E10 -> 13.545541
A28: Navigate via the sheet tabs: Assumptions → Data → Ratios / Common-Size / DuPont → Forecast → DCF → Comps → Scenario Tool → Scorecard → Charts.

Sheet Assumptions
A1: Assumptions & Scenario Drivers
A2: Blue = editable input. Yellow = key assumption. Switch the case in the green box to flex the whole model.
A4: Foreign exchange (context only — all ratios are currency-neutral)
A5: Pair | B5: Rate | C5: Use
A6: USD / INR | B6: 85 | C6: USD-equivalents for HAL
A7: EUR / USD | B7: 1.08 | C7: USD-equivalents for Dassault
A8: EUR / INR | B8: 92 | C8: Cross reference
A10: ★ Active scenario case
A11: Select case → | B11: Base | C11: Drives HAL forecast growth, margins, capex, WACC and DCF value.
A13: Forecast drivers (5-year HAL model)
A14: Driver | B14: Bull | C14: Base | D14: Bear | E14: Active
A15: Revenue growth (annual) | B15: 0.16 | C15: 0.13 | D15: 0.09 | E15: =IF($B$11="Bull",B15,IF($B$11="Base",C15,D15)) -> 0.13
A16: EBITDA margin | B16: 0.31 | C16: 0.295 | D16: 0.27 | E16: =IF($B$11="Bull",B16,IF($B$11="Base",C16,D16)) -> 0.295
A17: Effective tax rate | B17: 0.25 | C17: 0.25 | D17: 0.26 | E17: =IF($B$11="Bull",B17,IF($B$11="Base",C17,D17)) -> 0.25
A18: Capex (% of revenue) | B18: 0.055 | C18: 0.06 | D18: 0.065 | E18: =IF($B$11="Bull",B18,IF($B$11="Base",C18,D18)) -> 0.06
A19: D&A (% of revenue) | B19: 0.04 | C19: 0.04 | D19: 0.04 | E19: =IF($B$11="Bull",B19,IF($B$11="Base",C19,D19)) -> 0.04
A20: ΔWorking capital (% of Δrevenue) | B20: 0.1 | C20: 0.12 | D20: 0.18 | E20: =IF($B$11="Bull",B20,IF($B$11="Base",C20,D20)) -> 0.12
A21: WACC (discount rate) | B21: 0.105 | C21: 0.11 | D21: 0.125 | E21: =IF($B$11="Bull",B21,IF($B$11="Base",C21,D21)) -> 0.11
A22: Terminal growth rate | B22: 0.055 | C22: 0.055 | D22: 0.05 | E22: =IF($B$11="Bull",B22,IF($B$11="Base",C22,D22)) -> 0.055

Sheet HAL_Data
A1: HAL — Source Data (₹ crore, consolidated)
A2: Source: HAL annual reports & BSE/NSE filings, FY22–FY26.
A4: Metric | B4: FY22 | C4: FY23 | D4: FY24 | E4: FY25 | F4: FY26
A5: Revenue | B5: 24620 | C5: 26927 | D5: 30381 | E5: 30981 | F5: 33089
A6: EBITDA | B6: 5415 | C6: 6686 | D6: 9752 | E6: 9621 | F6: 9770
A7: Other income | B7: 985 | C7: 1673 | D7: 1923 | E7: 2608 | F7: 3743
A8: Interest | B8: 65 | C8: 64 | D8: 43 | E8: 22 | F8: 6
A9: Depreciation | B9: 1111 | C9: 1785 | D9: 1407 | E9: 1340 | F9: 1355
A10: PBT | B10: 5225 | C10: 6510 | D10: 10225 | E10: 10867 | F10: 12152
A11: Net profit | B11: 5080 | C11: 5828 | D11: 7621 | E11: 8364 | F11: 9116
A12: Expenses (COGS+opex) | B12: 19205 | C12: 20242 | D12: 20630 | E12: 21360 | F12: 23319
A13: Shareholders' equity | B13: 19313 | C13: 23572 | D13: 29138 | E13: 34981 | F13: 41041
A14: Borrowings | B14: 49 | C14: 52 | D14: 50 | E14: 51 | F14: 11
A15: Total assets | B15: 60254 | C15: 69276 | D15: 80911 | E15: 108698 | F15: 132415
A16: Inventory days | B16: 607 | C16: 527 | D16: 544 | E16: 736 | F16: 780
... A23: Order book (approx ₹cr) | B23: 84000 | C23: 94000 | D23: 131000 | E23: 184000 | F23: 220000

Sheet Dassault_Data
A1: Dassault Aviation — Source Data (€ million, adjusted)
A2: Source: Dassault annual reports & financial releases 2021–2025.
A4: Metric | B4: 2021 | C4: 2022 | D4: 2023 | E4: 2024 | F4: 2025
A5: Adj. net sales | B5: 7234 | C5: 6930 | D5: 4805 | E5: 6212 | F5: 7424
A6: Adj. operating income | B6: 527 | C6: 572 | D6: 349 | E6: 519 | F6: 635
A7: Adj. net income | B7: 693 | C7: 830 | D7: 886 | E7: 1056 | F7: 1061
A8: of which Thales | B8: 336 | C8: 386 | D8: 450 | E8: 507 | F8: 534
A9: Self-funded R&D | B9: 430 | C9: 572 | D9: 483 | E9: 437 | F9: 389
A10: Order backlog | B10: 20760 | C10: 35000 | D10: 38508 | E10: 43224 | F10: 46600
A11: Order intake | B11: 12080 | C11: 20954 | D11: 5000 | E11: 10870 | F11: 10940
A12: Available cash | B12: 4870 | C12: 6500 | D12: 7294 | E12: 8434 | F12: 9400
A13: EPS (€) | B13: 8.34 | C13: 9.99 | D13: 10.95 | E13: 13.46 | F13: 13.6
A14: Dividend / share (€) | B14: 2.49 | C14: 3.37 | D14: 3.37 | E14: 4.72 | F14: 4.78

Sheet Lockheed_Data
A1: Lockheed Martin — Source Data ($ million)
A2: Source: Lockheed Martin 10-K & earnings releases 2021–2025.
A4: Metric | B4: 2021 | C4: 2022 | D4: 2023 | E4: 2024 | F4: 2025
A5: Revenue | B5: 67044 | C5: 65984 | D5: 67571 | E5: 71043 | F5: 75048
A6: Gross profit | B6: 9061 | C6: 8287 | D6: 8479 | E6: 7619 | F6: 7374
A7: EBIT | B7: 9123 | C7: 8348 | D7: 8507 | E7: 7013 | F7: 7422
A8: Net income | B8: 6315 | C8: 5732 | D8: 6920 | E8: 5336 | F8: 5017
A9: Shareholders' equity | B9: 6142 | C9: 9266 | D9: 6835 | E9: 6333 | F9: 6700
A10: Total assets | B10: 50873 | C10: 52880 | D10: 52456 | E10: 53815 | F10: 55000
A11: Net debt | B11: 8072 | C11: 12882 | D11: 16017 | E11: 17787 | F11: 17579
A12: CapEx | B12: 1522 | C12: 1670 | D12: 1691 | E12: 1685 | F12: 1649
A13: Free cash flow | B13: 7699 | C13: 6132 | D13: 6229 | E13: 5287 | F13: 6908
A14: Order backlog | B14: 135900 | C14: 150000 | D14: 160600 | E14: 176000 | F14: 194000
A15: EPS ($) | B15: 22.76 | C15: 21.66 | D15: 27.55 | E15: 22.31 | F15: 21.49
A16: EBITDA margin | B16: 0.1564 | C16: 0.1478 | D16: 0.1471 | E16: 0.1207 | F16: 0.1255

Sheet Ratios
A1: Computed Ratios — live formulas
A2: Green = pulls from a data sheet. Colour scale: red (low) → green (high) within each row.
A4: HAL
A5: Ratio | B5: FY22 | C5: FY23 | D5: FY24 | E5: FY25 | F5: FY26
A6: Net margin | B6: =HAL_Data!B11/HAL_Data!B5 -> 0.20633631 | C6: =HAL_Data!C11/HAL_Data!C5 -> 0.21643703 | D6: =HAL_Data!D11/HAL_Data!D5 -> 0.25084757 | E6: =HAL_Data!E11/HAL_Data!E5 -> 0.26997192 | F6: =HAL_Data!F11/HAL_Data!F5 -> 0.27549941
A7: EBITDA margin | B7: =HAL_Data!B6/HAL_Data!B5 -> 0.21994314 | C7: =HAL_Data!C6/HAL_Data!C5 -> 0.24830096 | D7: =HAL_Data!D6/HAL_Data!D5 -> 0.32099009 | E7: =HAL_Data!E6/HAL_Data!E5 -> 0.31054517 | F7: =HAL_Data!F6/HAL_Data!F5 -> 0.29526429
A8: ROE | B8: =HAL_Data!B11/HAL_Data!B13 -> 0.26303526 | C8: =HAL_Data!C11/HAL_Data!C13 -> 0.24724249 | D8: =HAL_Data!D11/HAL_Data!D13 -> 0.26154849 | E8: =HAL_Data!E11/HAL_Data!E13 -> 0.23910123 | F8: =HAL_Data!F11/HAL_Data!F13 -> 0.22211934
A9: ROA | B9: =HAL_Data!B11/HAL_Data!B15 -> 0.084309755 | C9: =HAL_Data!C11/HAL_Data!C15 -> 0.084127259 | D9: =HAL_Data!D11/HAL_Data!D15 -> 0.094189912 | E9: =HAL_Data!E11/HAL_Data!E15 -> 0.076947138 | F9: =HAL_Data!F11/HAL_Data!F15 -> 0.068844164
A10: Net debt / EBITDA | B10: =(HAL_Data!B14-HAL_Data!B11)/HAL_Data!B6 -> -0.92908587 | C10: =(HAL_Data!C14-HAL_Data!C11)/HAL_Data!C6 -> -0.86389471 | D10: =(HAL_Data!D14-HAL_Data!D11)/HAL_Data!D6 -> -0.77635357 | E10: =(HAL_Data!E14-HAL_Data!E11)/HAL_Data!E6 -> -0.8640474 | F10: =(HAL_Data!F14-HAL_Data!F11)/HAL_Data!F6 -> -0.93193449
A12: Dassault (adjusted)
A13: Ratio | B13: 2021 | C13: 2022 | D13: 2023 | E13: 2024 | F13: 2025
A14: Net margin (reported) | B14: =Dassault_Data!B7/Dassault_Data!B5 -> 0.095797622 | C14: =Dassault_Data!C7/Dassault_Data!C5 -> 0.11976912 | D14: =Dassault_Data!D7/Dassault_Data!D5 -> 0.18439126 | E14: =Dassault_Data!E7/Dassault_Data!E5 -> 0.16999356 | F14: =Dassault_Data!F7/Dassault_Data!F5 -> 0.14291487
A15: Net margin (ex-Thales) | B15: =(Dassault_Data!B7-Dassault_Data!B8)/Dassault_Data!B5 -> 0.04935029 | C15: =(Dassault_Data!C7-Dassault_Data!C8)/Dassault_Data!C5 -> 0.064069264 | D15: =(Dassault_Data!D7-Dassault_Data!D8)/Dassault_Data!D5 -> 0.090738814 | E15: =(Dassault_Data!E7-Dassault_Data!E8)/Dassault_Data!E5 -> 0.088377334 | F15: =(Dassault_Data!F7-Dassault_Data!F8)/Dassault_Data!F5 -> 0.070985991
A16: Operating margin | B16: =Dassault_Data!B6/Dassault_Data!B5 -> 0.072850429 | C16: =Dassault_Data!C6/Dassault_Data!C5 -> 0.082539683 | D16: =Dassault_Data!D6/Dassault_Data!D5 -> 0.072632674 | E16: =Dassault_Data!E6/Dassault_Data!E5 -> 0.083547972 | F16: =Dassault_Data!F6/Dassault_Data!F5 -> 0.085533405
A17: Self-funded R&D % sales | B17: =Dassault_Data!B9/Dassault_Data!B5 -> 0.059441526 | C17: =Dassault_Data!C9/Dassault_Data!C5 -> 0.082539683 | D17: =Dassault_Data!D9/Dassault_Data!D5 -> 0.10052029 | E17: =Dassault_Data!E9/Dassault_Data!E5 -> 0.070347714 | F17: =Dassault_Data!F9/Dassault_Data!F5 -> 0.052397629
A19: Lockheed Martin
A20: Ratio | B20: 2021 | C20: 2022 | D20: 2023 | E20: 2024 | F20: 2025
A21: Net margin | B21: =Lockheed_Data!B8/Lockheed_Data!B5 -> 0.094191874 | C21: =Lockheed_Data!C8/Lockheed_Data!C5 -> 0.086869544 | D21: =Lockheed_Data!D8/Lockheed_Data!D5 -> 0.1024108 | E21: =Lockheed_Data!E8/Lockheed_Data!E5 -> 0.075109441 | F21: =Lockheed_Data!F8/Lockheed_Data!F5 -> 0.066850549
A22: Gross margin | B22: =Lockheed_Data!B6/Lockheed_Data!B5 -> 0.13515005 | C22: =Lockheed_Data!C6/Lockheed_Data!C5 -> 0.12559105 | D22: =Lockheed_Data!D6/Lockheed_Data!D5 -> 0.12548283 | E22: =Lockheed_Data!E6/Lockheed_Data!E5 -> 0.10724491 | F22: =Lockheed_Data!F6/Lockheed_Data!F5 -> 0.098257115
A23: EBIT margin | B23: =Lockheed_Data!B7/Lockheed_Data!B5 -> 0.13607482 | C23: =Lockheed_Data!C7/Lockheed_Data!C5 -> 0.12651552 | D23: =Lockheed_Data!D7/Lockheed_Data!D5 -> 0.1258972 | E23: =Lockheed_Data!E7/Lockheed_Data!E5 -> 0.098714863 | F23: =Lockheed_Data!F7/Lockheed_Data!F5 -> 0.098896706
A24: ROA | B24: =Lockheed_Data!B8/Lockheed_Data!B10 -> 0.12413264 | C24: =Lockheed_Data!C8/Lockheed_Data!C10 -> 0.10839637 | D24: =Lockheed_Data!D8/Lockheed_Data!D10 -> 0.13192009 | E24: =Lockheed_Data!E8/Lockheed_Data!E10 -> 0.099154511 | F24: =Lockheed_Data!F8/Lockheed_Data!F10 -> 0.091218182
A25: Net debt / EBITDA | B25: =Lockheed_Data!B11/(Lockheed_Data!B5*Lockheed_Data!B16) -> 0.76981166 | C25: =Lockheed_Data!C11/(Lockheed_Data!C5*Lockheed_Data!C16) -> 1.3209009 | D25: =Lockheed_Data!D11/(Lockheed_Data!D5*Lockheed_Data!D16) -> 1.6114178 | E25: =Lockheed_Data!E11/(Lockheed_Data!E5*Lockheed_Data!E16) -> 2.0743123 | F25: =Lockheed_Data!F11/(Lockheed_Data!F5*Lockheed_Data!F16) -> 1.8664283

Sheet Common_Size
A1: Common-Size Income Statements (% of revenue)
A2: Normalises three very different-sized firms onto one comparable basis (latest 5 years).
A4: HAL
A5: Line (% of revenue) | B5: FY22 | C5: FY23 | D5: FY24 | E5: FY25 | F5: FY26
A6: EBITDA | B6: =HAL_Data!B6/HAL_Data!B5 -> 0.21994314 | C6: =HAL_Data!C6/HAL_Data!C5 -> 0.24830096 | D6: =HAL_Data!D6/HAL_Data!D5 -> 0.32099009 | E6: =HAL_Data!E6/HAL_Data!E5 -> 0.31054517 | F6: =HAL_Data!F6/HAL_Data!F5 -> 0.29526429
A7: Depreciation | B7: =HAL_Data!B9/HAL_Data!B5 -> 0.045125914 | C7: =HAL_Data!C9/HAL_Data!C5 -> 0.066290341 | D7: =HAL_Data!D9/HAL_Data!D5 -> 0.04631184 | E7: =HAL_Data!E9/HAL_Data!E5 -> 0.043252316 | F7: =HAL_Data!F9/HAL_Data!F5 -> 0.040950165
A8: Net profit | B8: =HAL_Data!B11/HAL_Data!B5 -> 0.20633631 | C8: =HAL_Data!C11/HAL_Data!C5 -> 0.21643703 | D8: =HAL_Data!D11/HAL_Data!D5 -> 0.25084757 | E8: =HAL_Data!E11/HAL_Data!E5 -> 0.26997192 | F8: =HAL_Data!F11/HAL_Data!F5 -> 0.27549941
A10: Dassault
A11: Line (% of revenue) | B11: 2021 | C11: 2022 | D11: 2023 | E11: 2024 | F11: 2025
A12: Operating income | B12: =Dassault_Data!B6/Dassault_Data!B5 -> 0.072850429 | C12: =Dassault_Data!C6/Dassault_Data!C5 -> 0.082539683 | D12: =Dassault_Data!D6/Dassault_Data!D5 -> 0.072632674 | E12: =Dassault_Data!E6/Dassault_Data!E5 -> 0.083547972 | F12: =Dassault_Data!F6/Dassault_Data!F5 -> 0.085533405
A13: Net income | B13: =Dassault_Data!B7/Dassault_Data!B5 -> 0.095797622 | C13: =Dassault_Data!C7/Dassault_Data!C5 -> 0.11976912 | D13: =Dassault_Data!D7/Dassault_Data!D5 -> 0.18439126 | E13: =Dassault_Data!E7/Dassault_Data!E5 -> 0.16999356 | F13: =Dassault_Data!F7/Dassault_Data!F5 -> 0.14291487
A14: Thales contribution | B14: =Dassault_Data!B8/Dassault_Data!B5 -> 0.046447332 | C14: =Dassault_Data!C8/Dassault_Data!C5 -> 0.055699856 | D14: =Dassault_Data!D8/Dassault_Data!D5 -> 0.093652445 | E14: =Dassault_Data!E8/Dassault_Data!E5 -> 0.081616227 | F14: =Dassault_Data!F8/Dassault_Data!F5 -> 0.071928879
A16: Lockheed Martin
A17: Line (% of revenue) | B17: 2021 | C17: 2022 | D17: 2023 | E17: 2024 | F17: 2025
A18: Gross profit | B18: =Lockheed_Data!B6/Lockheed_Data!B5 -> 0.13515005 | C18: =Lockheed_Data!C6/Lockheed_Data!C5 -> 0.12559105 | D18: =Lockheed_Data!D6/Lockheed_Data!D5 -> 0.12548283 | E18: =Lockheed_Data!E6/Lockheed_Data!E5 -> 0.10724491 | F18: =Lockheed_Data!F6/Lockheed_Data!F5 -> 0.098257115
A19: EBIT | B19: =Lockheed_Data!B7/Lockheed_Data!B5 -> 0.13607482 | C19: =Lockheed_Data!C7/Lockheed_Data!C5 -> 0.12651552 | D19: =Lockheed_Data!D7/Lockheed_Data!D5 -> 0.1258972 | E19: =Lockheed_Data!E7/Lockheed_Data!E5 -> 0.098714863 | F19: =Lockheed_Data!F7/Lockheed_Data!F5 -> 0.098896706
A20: Net income | B20: =Lockheed_Data!B8/Lockheed_Data!B5 -> 0.094191874 | C20: =Lockheed_Data!C8/Lockheed_Data!C5 -> 0.086869544 | D20: =Lockheed_Data!D8/Lockheed_Data!D5 -> 0.1024108 | E20: =Lockheed_Data!E8/Lockheed_Data!E5 -> 0.075109441 | F20: =Lockheed_Data!F8/Lockheed_Data!F5 -> 0.066850549

Sheet DuPont
A1: DuPont Decomposition of ROE (latest year)
A2: ROE = Net margin × Asset turnover × Equity multiplier. *Dassault assets/equity approximate.
A4: Company | B4: Net margin | C4: Asset turnover | D4: Equity multiplier | E4: ROE (=product)
A5: HAL | B5: =HAL_Data!F11/HAL_Data!F5 -> 0.27549941 | C5: =HAL_Data!F5/HAL_Data!F15 -> 0.24988861 | D5: =HAL_Data!F15/HAL_Data!F13 -> 3.2264077 | E5: =B5*C5*D5 -> 0.22211934 | G5: Dassault inputs (€m):
A6: Dassault* | B6: =Dassault_Data!F7/Dassault_Data!F5 -> 0.14291487 | C6: =Dassault_Data!F5/H6 -> 0.35352381 | D6: =H6/H7 -> 4.7727273 | E6: =B6*C6*D6 -> 0.24113636 | G6: Assets | H6: 21000
A7: Lockheed Martin | B7: =Lockheed_Data!F8/Lockheed_Data!F5 -> 0.066850549 | C7: =Lockheed_Data!F5/Lockheed_Data!F10 -> 1.3645091 | D7: =Lockheed_Data!F10/Lockheed_Data!F9 -> 8.2089552 | E7: =B7*C7*D7 -> 0.74880597 | G7: Equity | H7: 4400
A9: Read: HAL & Dassault reach a similar ROE by different routes (HAL via margin); Lockheed's high ROE is mostly leverage (equity multiplier > 8×).

Sheet HAL_Forecast
A1: HAL — 5-Year Forecast Model (₹ crore)
A2: Driver-based projection. All drivers flow from the Assumptions sheet (active scenario case).
A4: Line item | B4: FY26 (base) | C4: FY27E | D4: FY28E | E4: FY29E | F4: FY30E | G4: FY31E
A5: Revenue | B5: =HAL_Data!F5 -> 33089 | C5: =B5*(1+Assumptions!$E$15) -> 37390.57 | D5: =C5*(1+Assumptions!$E$15) -> 42251.344 | E5: =D5*(1+Assumptions!$E$15) -> 47744.019 | F5: =E5*(1+Assumptions!$E$15) -> 53950.741 | G5: =F5*(1+Assumptions!$E$15) -> 60964.338
A6: growth % | C6: =C5/B5-1 -> 0.13 | D6: =D5/C5-1 -> 0.13 | E6: =E5/D5-1 -> 0.13 | F6: =F5/E5-1 -> 0.13 | G6: =G5/F5-1 -> 0.13
A7: EBITDA | B7: =HAL_Data!F6 -> 9770 | C7: =C5*Assumptions!$E$16 -> 11030.218 | D7: =D5*Assumptions!$E$16 -> 12464.147 | E7: =E5*Assumptions!$E$16 -> 14084.486 | F7: =F5*Assumptions!$E$16 -> 15915.469 | G7: =G5*Assumptions!$E$16 -> 17984.48
A8: Depreciation & amort. | B8: =HAL_Data!F9 -> 1355 | C8: =-C5*Assumptions!$E$19 -> -1495.6228 | D8: =-D5*Assumptions!$E$19 -> -1690.0538 | E8: =-E5*Assumptions!$E$19 -> -1909.7608 | F8: =-F5*Assumptions!$E$19 -> -2158.0297 | G8: =-G5*Assumptions!$E$19 -> -2438.5735
A9: EBIT | B9: =B7+B8 -> 11125 | C9: =C7+C8 -> 9534.5953 | D9: =D7+D8 -> 10774.093 | E9: =E7+E8 -> 12174.725 | F9: =F7+F8 -> 13757.439 | G9: =G7+G8 -> 15545.906
A10: Tax | B10: =-B9*0.25 -> -2781.25 | C10: =-C9*Assumptions!$E$17 -> -2383.6488 | D10: =-D9*Assumptions!$E$17 -> -2693.5232 | E10: =-E9*Assumptions!$E$17 -> -3043.6812 | F10: =-F9*Assumptions!$E$17 -> -3439.3598 | G10: =-G9*Assumptions!$E$17 -> -3886.4765
A11: NOPAT | B11: =B9+B10 -> 8343.75 | C11: =C9+C10 -> 7150.9465 | D11: =D9+D10 -> 8080.5696 | E11: =E9+E10 -> 9131.0436 | F11: =F9+F10 -> 10318.079 | G11: =G9+G10 -> 11659.43
A12: Capex | B12: =-HAL_Data!F5*0.06 -> -1985.34 | C12: =-C5*Assumptions!$E$18 -> -2243.4342 | D12: =-D5*Assumptions!$E$18 -> -2535.0806 | E12: =-E5*Assumptions!$E$18 -> -2864.6411 | F12: =-F5*Assumptions!$E$18 -> -3237.0445 | G12: =-G5*Assumptions!$E$18 -> -3657.8603
A13: Δ Revenue | C13: =C5-B5 -> 4301.57 | D13: =D5-C5 -> 4860.7741 | E13: =E5-D5 -> 5492.6747 | F13: =F5-E5 -> 6206.7224 | G13: =G5-F5 -> 7013.5964
A14: Δ Working capital | C14: =-C13*Assumptions!$E$20 -> -516.1884 | D14: =-D13*Assumptions!$E$20 -> -583.29289 | E14: =-E13*Assumptions!$E$20 -> -659.12097 | F14: =-F13*Assumptions!$E$20 -> -744.80669 | G14: =-G13*Assumptions!$E$20 -> -841.63156
A15: Free cash flow to firm (FCFF) | C15: =C11-C8+C12+C14 -> 5886.9467 | D15: =D11-D8+D12+D14 -> 6652.2498 | E15: =E11-E8+E12+E14 -> 7517.0423 | F15: =F11-F8+F12+F14 -> 8494.2578 | G15: =G11-G8+G12+G14 -> 9598.5113
A17: Note: D&A and capex shown as negatives in the build. FCFF = NOPAT + D&A − Capex − ΔWC. Drivers are on the Assumptions sheet.

Sheet DCF_Valuation
A1: HAL — DCF Valuation & Sensitivity
A2: Discounts the forecast FCFF at WACC; terminal value via Gordon growth. Inputs in blue; case-driven cells in green.
A4: Key inputs
A5: WACC (from active case) | C5: =Assumptions!E21 -> 0.11
A6: Terminal growth (from active case) | C6: =Assumptions!E22 -> 0.055
A7: Net cash (₹cr, approx) | C7: 25000
A8: Shares outstanding (crore) | C8: 66.84
A9: Current share price (₹) | C9: 4255
A11: Valuation build
A12: PV of explicit FCFF (FY27–31) | C12: =NPV(C5,HAL_Forecast!C15:G15) -> 27490.747
A13: Terminal value (end FY31) | C13: =HAL_Forecast!G15*(1+C6)/(C5-C6) -> 184116.9
A14: PV of terminal value | C14: =C13/(1+C5)^5 -> 109264.42
A15: Enterprise value | C15: =C12+C14 -> 136755.16
A16: (+) Net cash | C16: =C7 -> 25000
A17: Equity value | C17: =C15+C16 -> 161755.16
A18: Value per share (₹) | C18: =C17/C8 -> 2420.0354
A19: Upside / (downside) vs price | C19: =C18/C9-1 -> -0.43124903
A22: Sensitivity — value per share (₹): WACC (down) × terminal growth (across)
B23: WACC ↓ / g → | C23: 0.045 | D23: 0.05 | E23: 0.055 | F23: 0.06 | G23: 0.065
B24: 0.095 | C24: =(NPV($B24,HAL_Forecast!$C$15:$G$15)+(HAL_Forecast!$G$15*(1+C$23)/($B24-C$23))/(1+$B24)^5+$C$7)/$C$8 -> 2709.2696 | D24: =(NPV($B24,HAL_Forecast!$C$15:$G$15)+(HAL_Forecast!$G$15*(1+D$23)/($B24-D$23))/(1+$B24)^5+$C$7)/$C$8 -> 2931.2418 | E24: =(NPV($B24,HAL_Forecast!$C$15:$G$15)+(HAL_Forecast!$G$15*(1+E$23)/($B24-E$23))/(1+$B24)^5+$C$7)/$C$8 -> 3208.7069 | F24: =(NPV($B24,HAL_Forecast!$C$15:$G$15)+(HAL_Forecast!$G$15*(1+F$23)/($B24-F$23))/(1+$B24)^5+$C$7)/$C$8 -> 3565.4478 | G24: =(NPV($B24,HAL_Forecast!$C$15:$G$15)+(HAL_Forecast!$G$15*(1+G$23)/($B24-G$23))/(1+$B24)^5+$C$7)/$C$8 -> 4041.1024
B25: 0.105 | C25: =(NPV($B25,HAL_Forecast!$C$15:$G$15)+(HAL_Forecast!$G$15*(1+C$23)/($B25-C$23))/(1+$B25)^5+$C$7)/$C$8 -> 2309.1759 | D25: =(NPV($B25,HAL_Forecast!$C$15:$G$15)+(HAL_Forecast!$G$15*(1+D$23)/($B25-D$23))/(1+$B25)^5+$C$7)/$C$8 -> 2455.1159 | E25: =(NPV($B25,HAL_Forecast!$C$15:$G$15)+(HAL_Forecast!$G$15*(1+E$23)/($B25-E$23))/(1+$B25)^5+$C$7)/$C$8 -> 2630.244 | F25: =(NPV($B25,HAL_Forecast!$C$15:$G$15)+(HAL_Forecast!$G$15*(1+F$23)/($B25-F$23))/(1+$B25)^5+$C$7)/$C$8 -> 2844.2893 | G25: =(NPV($B25,HAL_Forecast!$C$15:$G$15)+(HAL_Forecast!$G$15*(1+G$23)/($B25-G$23))/(1+$B25)^5+$C$7)/$C$8 -> 3111.846
B26: 0.11 | C26: =(NPV($B26,HAL_Forecast!$C$15:$G$15)+(HAL_Forecast!$G$15*(1+C$23)/($B26-C$23))/(1+$B26)^5+$C$7)/$C$8 -> 2155.4295 | D26: =(NPV($B26,HAL_Forecast!$C$15:$G$15)+(HAL_Forecast!$G$15*(1+D$23)/($B26-D$23))/(1+$B26)^5+$C$7)/$C$8 -> 2276.7072 | E26: =(NPV($B26,HAL_Forecast!$C$15:$G$15)+(HAL_Forecast!$G$15*(1+E$23)/($B26-E$23))/(1+$B26)^5+$C$7)/$C$8 -> 2420.0354 | F26: =(NPV($B26,HAL_Forecast!$C$15:$G$15)+(HAL_Forecast!$G$15*(1+F$23)/($B26-F$23))/(1+$B26)^5+$C$7)/$C$8 -> 2592.0292 | G26: =(NPV($B26,HAL_Forecast!$C$15:$G$15)+(HAL_Forecast!$G$15*(1+G$23)/($B26-G$23))/(1+$B26)^5+$C$7)/$C$8 -> 2802.2439
B27: 0.12 | C27: =(NPV($B27,HAL_Forecast!$C$15:$G$15)+(HAL_Forecast!$G$15*(1+C$23)/($B27-C$23))/(1+$B27)^5+$C$7)/$C$8 -> 1909.6614 | D27: =(NPV($B27,HAL_Forecast!$C$15:$G$15)+(HAL_Forecast!$G$15*(1+D$23)/($B27-D$23))/(1+$B27)^5+$C$7)/$C$8 -> 1996.5787 | E27: =(NPV($B27,HAL_Forecast!$C$15:$G$15)+(HAL_Forecast!$G$15*(1+E$23)/($B27-E$23))/(1+$B27)^5+$C$7)/$C$8 -> 2096.8679 | F27: =(NPV($B27,HAL_Forecast!$C$15:$G$15)+(HAL_Forecast!$G$15*(1+F$23)/($B27-F$23))/(1+$B27)^5+$C$7)/$C$8 -> 2213.8719 | G27: =(NPV($B27,HAL_Forecast!$C$15:$G$15)+(HAL_Forecast!$G$15*(1+G$23)/($B27-G$23))/(1+$B27)^5+$C$7)/$C$8 -> 2352.1493
B28: 0.13 | C28: =(NPV($B28,HAL_Forecast!$C$15:$G$15)+(HAL_Forecast!$G$15*(1+C$23)/($B28-C$23))/(1+$B28)^5+$C$7)/$C$8 -> 1721.9771 | D28: =(NPV($B28,HAL_Forecast!$C$15:$G$15)+(HAL_Forecast!$G$15*(1+D$23)/($B28-D$23))/(1+$B28)^5+$C$7)/$C$8 -> 1786.7382 | E28: =(NPV($B28,HAL_Forecast!$C$15:$G$15)+(HAL_Forecast!$G$15*(1+E$23)/($B28-E$23))/(1+$B28)^5+$C$7)/$C$8 -> 1860.1342 | F28: =(NPV($B28,HAL_Forecast!$C$15:$G$15)+(HAL_Forecast!$G$15*(1+F$23)/($B28-F$23))/(1+$B28)^5+$C$7)/$C$8 -> 1944.0154 | G28: =(NPV($B28,HAL_Forecast!$C$15:$G$15)+(HAL_Forecast!$G$15*(1+G$23)/($B28-G$23))/(1+$B28)^5+$C$7)/$C$8 -> 2040.8013
A30: Illustrative DCF on public data — NOT a price target. A standard DCF tends to value HAL below its market price: the market embeds a multi-year defence super-cycle and export optionality beyond this 5-year window. Read the sensitivity grid as a range, and treat the gap to market as 'growth priced in', not as a call. Net cash & price are editable.

Sheet Valuation_Summary
A1: Football-Field Valuation Summary — HAL
A2: Each method is a RANGE, not a point estimate. DCF range flexes with the active case on Assumptions. Illustrative — not a price target.
A4: Shared inputs (linked to the model)
A5: HAL EPS (FY26, ₹) | C5: =HAL_Data!F21 -> 136.3
A6: HAL EBITDA (FY26, ₹cr) | C6: =HAL_Data!F6 -> 9770
A7: Net cash (₹cr) | C7: =DCF_Valuation!C7 -> 25000
A8: Shares outstanding (crore) | C8: =DCF_Valuation!C8 -> 66.84
A9: Current market price (₹) | C9: =DCF_Valuation!C9 -> 4255
A11: Valuation ranges (₹ per share)
A12: Method | B12: Low | C12: High | D12: Midpoint | E12: Basis | G12: Base (hidden) | H12: Span
A13: DCF — WACC × terminal growth | B13: =MIN(DCF_Valuation!C24:G28) -> 1721.9771 | C13: =MAX(DCF_Valuation!C24:G28) -> 4041.1024 | D13: =AVERAGE(B13:C13) -> 2881.5397 | E13: Full sensitivity grid (live) | G13: =B13 -> 1721.9771 | H13: =C13-B13 -> 2319.1253
A14: Peer P/E applied to HAL EPS | B14: =MIN(Comps!D11,Comps!E11)*$C$5 -> 1785.6456 | C14: =MAX(Comps!D11,Comps!E11)*$C$5 -> 2988.4393 | D14: =AVERAGE(B14:C14) -> 2387.0425 | E14: Dassault & Lockheed P/E × HAL EPS | G14: =B14 -> 1785.6456 | H14: =C14-B14 -> 1202.7937
A15: Peer EV/EBITDA applied to HAL | B15: =(MIN(Comps!D10,Comps!E10)*$C$6+$C$7)/$C$8 -> 1409.8776 | C15: =(MAX(Comps!D10,Comps!E10)*$C$6+$C$7)/$C$8 -> 2353.9786 | D15: =AVERAGE(B15:C15) -> 1881.9281 | E15: Peer EV/EBITDA × HAL EBITDA + net cash | G15: =B15 -> 1409.8776 | H15: =C15-B15 -> 944.10102
A16: HAL's own trading range | B16: =25*$C$5 -> 3407.5 | C16: =40*$C$5 -> 5452 | D16: =AVERAGE(B16:C16) -> 4429.75 | E16: ~25×–40× earnings (editable) | G16: =B16 -> 3407.5 | H16: =C16-B16 -> 2044.5
A18: Market price (₹) | B18: =$C$9 -> 4255 | C18: ← compare each range against this
A20: Chart: the coloured bar spans Low → High for each method. Compare the clustering against the market price above.

Sheet Comps
A1: Relative Valuation (Comps)
A2: Market multiples across the three. Market caps in blue (indicative, native currency).
A4: Metric | B4: HAL (₹cr) | C4: Dassault (€m) | D4: Lockheed ($m)
A5: Market capitalisation | C5: 284544 | D5: 13900 | E5: 110000
A6: (+) Net debt / (− net cash) | C6: =-DCF_Valuation!C7 -> -25000 | D6: =-Dassault_Data!F12 -> -9400 | E6: =Lockheed_Data!F11 -> 17579
A7: Enterprise value (EV) | C7: =C5+C6 -> 259544 | D7: =D5+D6 -> 4500 | E7: =E5+E6 -> 127579
A8: EBITDA | C8: =HAL_Data!F6 -> 9770 | D8: =Dassault_Data!F6 -> 635 | E8: =Lockheed_Data!F5*Lockheed_Data!F16 -> 9418.524
A9: Net income | C9: =HAL_Data!F11 -> 9116 | D9: =Dassault_Data!F7 -> 1061 | E9: =Lockheed_Data!F8 -> 5017
A10: EV / EBITDA | C10: =C7/C8 -> 26.565404 | D10: =D7/D8 -> 7.0866142 | E10: =E7/E8 -> 13.545541
A11: P / E | C11: =C5/C9 -> 31.21369 | D11: =D5/D9 -> 13.100848 | E11: =E5/E9 -> 21.925453
A12: Revenue | C12: =HAL_Data!F5 -> 33089 | D12: =Dassault_Data!F5 -> 7424 | E12: =Lockheed_Data!F5 -> 75048
A13: EV / Sales | C13: =C7/C11 -> 8315.0694 | D13: =D7/D11 -> 343.48921 | E13: =E7/E11 -> 5818.7622
A15: Caveats: market caps are indicative point-in-time inputs; HAL net cash links to the DCF assumption. Multiples are cross-currency-consistent (each in its own currency).

Sheet Scenario_Tool
A1: ★ Working-Capital Scenario Tool
A2: Independent what-if on inventory efficiency. Pick options in the yellow dropdowns.
A4: Step 1 — inventory-day reduction scenario: | D4: Base case
A5: Step 2 — benchmark HAL against: | D5: Dassault
A7: Scenario assumptions (editable)
A8: Scenario | B8: Inv-day reduction
A9: Conservative | B9: 0.05
A10: Base case | B10: 0.1
A11: Aggressive | B11: 0.15
A13: Cash-release calculation
A14: Current inventory days (FY26) | D14: =HAL_Data!F16 -> 780
A15: Annual COGS / expenses (FY26, ₹cr) | D15: =HAL_Data!F12 -> 23319
A16: Selected reduction % | D16: =INDEX($B$9:$B$11,MATCH($D$4,$A$9:$A$11,0)) -> 0.1
A17: New inventory days | D17: =D14*(1-D16) -> 702
A18: Inventory days saved | D18: =D14-D17 -> 78
A19: Implied inventory value today (₹cr) | D19: =D14/365*D15 -> 49832.384
A20: ➤ CASH RELEASED (₹ crore) | D20: =D18/365*D15 -> 4983.2384
A23: HAL vs selected peer — latest year
A24: Metric | B24: HAL | C24: Selected peer
A25: Net margin | B25: =HAL_Data!F11/HAL_Data!F5 -> 0.27549941 | C25: =IF($D$5="Dassault",Dassault_Data!F7/Dassault_Data!F5,Lockheed_Data!F8/Lockheed_Data!F5) -> 0.14291487
A26: Revenue CAGR (5-yr) | B26: =POWER(HAL_Data!F5/HAL_Data!B5,1/4)-1 -> 0.076710376 | C26: =IF($D$5="Dassault",POWER(Dassault_Data!F5/Dassault_Data!B5,1/4)-1,POWER(Lockheed_Data!F5/Lockheed_Data!B5,1/4)-1) -> 0.0065025156
A27: Net debt / EBITDA | B27: =(HAL_Data!F14-HAL_Data!F11)/HAL_Data!F6 -> -0.93193449 | C27: =IF($D$5="Dassault",-2.5,Lockheed_Data!F11/(Lockheed_Data!F5*Lockheed_Data!F16)) -> -2.5

Sheet Scorecard
A1: Benchmarking Scorecard
A2: A = HAL clearly stronger → D = HAL clearly weaker, relative to that peer.
A4: Parameter | B4: HAL vs Dassault | C4: HAL vs Lockheed | D4: Comment
A5: Profitability (margins) | B5: A | C5: B | D5: HAL ahead; Dassault flattered by Thales
A6: Returns quality (ROA/ROCE) | B6: A | C6: B | D6: HAL high-quality; LMT ROE via leverage
A7: Liquidity / net cash | B7: A | C7: A | D7: HAL & Dassault net-cash; LMT levered
A8: Solvency / leverage | B8: A | C8: B | D8: HAL near debt-free
A9: Efficiency / working capital | B9: D | C9: C | D9: HAL's main weakness — inventory lock-up
A10: Revenue growth | B10: A | C10: B | D10: HAL fastest & steadiest
A11: Order-book visibility | B11: B | C11: A | D11: All strong; Dassault deepest cover
A12: R&D intensity (on-books) | B12: C | C12: D | D12: Misleading — much HAL R&D off-books
A13: IP / design authority | B13: C | C13: D | D13: Peers own platform IP
A14: Diversification | B14: D | C14: B | D14: HAL & Dassault concentrated; LMT broad
A15: Capital return to holders | B15: B | C15: A | D15: LMT & Dassault higher payout
A16: Valuation / growth premium | B16: A | C16: A | D16: Market already rewards HAL

Sheet Charts
A1: Visual Trends
A2: Charts read live from the data sheets.
A4: Net margin (%)
A5: Year | B5: HAL | C5: Dassault | D5: Lockheed
A6: Y1 | B6: =HAL_Data!B11/HAL_Data!B5 -> 0.20633631 | C6: =Dassault_Data!B7/Dassault_Data!B5 -> 0.095797622 | D6: =Lockheed_Data!B8/Lockheed_Data!B5 -> 0.094191874
A7: Y2 | B7: =HAL_Data!C11/HAL_Data!C5 -> 0.21643703 | C7: =Dassault_Data!C7/Dassault_Data!C5 -> 0.11976912 | D7: =Lockheed_Data!C8/Lockheed_Data!C5 -> 0.086869544
A8: Y3 | B8: =HAL_Data!D11/HAL_Data!D5 -> 0.25084757 | C8: =Dassault_Data!D7/Dassault_Data!D5 -> 0.18439126 | D8: =Lockheed_Data!D8/Lockheed_Data!D5 -> 0.1024108
A9: Y4 | B9: =HAL_Data!E11/HAL_Data!E5 -> 0.26997192 | C9: =Dassault_Data!E7/Dassault_Data!E5 -> 0.16999356 | D9: =Lockheed_Data!E8/Lockheed_Data!E5 -> 0.075109441
A10: Y5 | B10: =HAL_Data!F11/HAL_Data!F5 -> 0.27549941 | C10: =Dassault_Data!F7/Dassault_Data!F5 -> 0.14291487 | D10: =Lockheed_Data!F8/Lockheed_Data!F5 -> 0.066850549
A13: HAL forecast revenue (₹cr)
A14: Year | B14: Revenue
A15: FY26 | B15: =HAL_Forecast!B5 -> 33089
A16: FY27E | B16: =HAL_Forecast!C5 -> 37390.57
A17: FY28E | B17: =HAL_Forecast!D5 -> 42251.344
A18: FY29E | B18: =HAL_Forecast!E5 -> 47744.019
A19: FY30E | B19: =HAL_Forecast!F5 -> 53950.741
A20: FY31E | B20: =HAL_Forecast!G5 -> 60964.338
