Workbook

Sheet Index
A1: Comparative Financial Analysis — HAL vs Dassault vs Lockheed Martin
A2: Interactive workbook • Public-domain data only • Not investment advice • June 2026
A4: Sheet | B4: What it contains
A5: Assumptions | B5: FX rates and global assumptions (blue = editable inputs)
A6: HAL_Data | B6: HAL five-year source data, ₹ crore (FY22–FY26)
A7: Dassault_Data | B7: Dassault five-year source data, € million (2021–2025, adjusted)
A8: Lockheed_Data | B8: Lockheed Martin five-year source data, $ million (2021–2025)
A9: Ratios | B9: All computed ratios via live formulas linking to the data sheets
A10: DuPont | B10: ROE decomposition: margin × asset turnover × leverage
A11: Scorecard | B11: A–D benchmarking of HAL against each peer
A12: Scenario_Tool | B12: ★ Interactive: choose a working-capital scenario & a peer to benchmark
A13: Charts | B13: Visual trends generated from the Ratios sheet
A15: Colour legend
A16: Blue text | B16: Hardcoded input — safe to change for scenarios
A17: Black text | B17: Formula / calculation
A18: Green text | B18: Link pulling from another sheet
A19: Yellow fill | B19: Key assumption to review

Sheet Assumptions
A1: Global Assumptions & FX
A2: Blue cells are editable. FX is for scale context only — all ratio comparisons are currency-neutral.
A4: Pair | B4: Rate | C4: Use
A5: USD / INR | B5: 85 | C5: USD-equivalents for HAL context
A6: EUR / USD | B6: 1.08 | C6: USD-equivalents for Dassault context
A7: EUR / INR | B7: 92 | C7: Cross-context reference
A9: Window: HAL FY2022–FY2026 (Mar y/e) ; Dassault & Lockheed CY2021–CY2025 (Dec y/e), aligned nearest-year.

Sheet HAL_Data
A1: HAL — Source Data (₹ crore, consolidated)
A2: Source: HAL annual reports & BSE/NSE filings FY22–FY26. Blue = input.
A4: Metric | B4: FY22 | C4: FY23 | D4: FY24 | E4: FY25 | F4: FY26
A5: Revenue | B5: 24620 | C5: 26927 | D5: 30381 | E5: 30981 | F5: 33089
A6: EBITDA | B6: 5415 | C6: 6686 | D6: 9752 | E6: 9621 | F6: 9770
A7: Other income | B7: 985 | C7: 1673 | D7: 1923 | E7: 2608 | F7: 3743
A8: Interest | B8: 65 | C8: 64 | D8: 43 | E8: 22 | F8: 6
A9: Depreciation | B9: 1111 | C9: 1785 | D9: 1407 | E9: 1340 | F9: 1355
A10: PBT | B10: 5225 | C10: 6510 | D10: 10225 | E10: 10867 | F10: 12152
A11: Net profit | B11: 5080 | C11: 5828 | D11: 7621 | E11: 8364 | F11: 9116
A12: Expenses (COGS+opex) | B12: 19205 | C12: 20242 | D12: 20630 | E12: 21360 | F12: 23319
A13: Shareholders' equity | B13: 19313 | C13: 23572 | D13: 29138 | E13: 34981 | F13: 41041
A14: Borrowings | B14: 49 | C14: 52 | D14: 50 | E14: 51 | F14: 11
A15: Total assets | B15: 60254 | C15: 69276 | D15: 80911 | E15: 108698 | F15: 132415
A16: Inventory days | B16: 607 | C16: 527 | D16: 544 | E16: 736 | F16: 780
... A23: Order book (approx ₹cr) | B23: 84000 | C23: 94000 | D23: 131000 | E23: 184000 | F23: 220000

Sheet Dassault_Data
A1: Dassault Aviation — Source Data (€ million, adjusted)
A2: Source: Dassault annual reports & financial releases 2021–2025. Blue = input.
A4: Metric | B4: 2021 | C4: 2022 | D4: 2023 | E4: 2024 | F4: 2025
A5: Adj. net sales | B5: 7234 | C5: 6930 | D5: 4805 | E5: 6212 | F5: 7424
A6: Adj. operating income | B6: 527 | C6: 572 | D6: 349 | E6: 519 | F6: 635
A7: Adj. net income | B7: 693 | C7: 830 | D7: 886 | E7: 1056 | F7: 1061
A8: of which Thales contribution | B8: 336 | C8: 386 | D8: 450 | E8: 507 | F8: 534
A9: Self-funded R&D | B9: 430 | C9: 572 | D9: 483 | E9: 437 | F9: 389
A10: Order backlog | B10: 20760 | C10: 35000 | D10: 38508 | E10: 43224 | F10: 46600
A11: Order intake | B11: 12080 | C11: 20954 | D11: 5000 | E11: 10870 | F11: 10940
A12: Available cash | B12: 4870 | C12: 6500 | D12: 7294 | E12: 8434 | F12: 9400
A13: EPS (€) | B13: 8.34 | C13: 9.99 | D13: 10.95 | E13: 13.46 | F13: 13.6
A14: Dividend / share (€) | B14: 2.49 | C14: 3.37 | D14: 3.37 | E14: 4.72 | F14: 4.78

Sheet Lockheed_Data
A1: Lockheed Martin — Source Data ($ million)
A2: Source: Lockheed Martin 10-K & earnings releases 2021–2025. Blue = input.
A4: Metric | B4: 2021 | C4: 2022 | D4: 2023 | E4: 2024 | F4: 2025
A5: Revenue | B5: 67044 | C5: 65984 | D5: 67571 | E5: 71043 | F5: 75048
A6: Gross profit | B6: 9061 | C6: 8287 | D6: 8479 | E6: 7619 | F6: 7374
A7: EBIT | B7: 9123 | C7: 8348 | D7: 8507 | E7: 7013 | F7: 7422
A8: Net income | B8: 6315 | C8: 5732 | D8: 6920 | E8: 5336 | F8: 5017
A9: Shareholders' equity | B9: 6142 | C9: 9266 | D9: 6835 | E9: 6333 | F9: 6700
A10: Total assets | B10: 50873 | C10: 52880 | D10: 52456 | E10: 53815 | F10: 55000
A11: Net debt | B11: 8072 | C11: 12882 | D11: 16017 | E11: 17787 | F11: 17579
A12: CapEx | B12: 1522 | C12: 1670 | D12: 1691 | E12: 1685 | F12: 1649
A13: Free cash flow | B13: 7699 | C13: 6132 | D13: 6229 | E13: 5287 | F13: 6908
A14: Order backlog | B14: 135900 | C14: 150000 | D14: 160600 | E14: 176000 | F14: 194000
A15: EPS ($) | B15: 22.76 | C15: 21.66 | D15: 27.55 | E15: 22.31 | F15: 21.49
A16: EBITDA margin | B16: 0.1564 | C16: 0.1478 | D16: 0.1471 | E16: 0.1207 | F16: 0.1255

Sheet Ratios
A1: Computed Ratios (live formulas)
A2: Black = formula; green = pulls from a data sheet. Edit any blue input on a data sheet and these update on recalc.
A4: HAL
A5: Ratio | B5: FY22 | C5: FY23 | D5: FY24 | E5: FY25 | F5: FY26
A6: Net margin | B6: =HAL_Data!B11/HAL_Data!B5 -> 0.20633631 | C6: =HAL_Data!C11/HAL_Data!C5 -> 0.21643703 | D6: =HAL_Data!D11/HAL_Data!D5 -> 0.25084757 | E6: =HAL_Data!E11/HAL_Data!E5 -> 0.26997192 | F6: =HAL_Data!F11/HAL_Data!F5 -> 0.27549941
A7: EBITDA margin | B7: =HAL_Data!B6/HAL_Data!B5 -> 0.21994314 | C7: =HAL_Data!C6/HAL_Data!C5 -> 0.24830096 | D7: =HAL_Data!D6/HAL_Data!D5 -> 0.32099009 | E7: =HAL_Data!E6/HAL_Data!E5 -> 0.31054517 | F7: =HAL_Data!F6/HAL_Data!F5 -> 0.29526429
A8: ROE | B8: =HAL_Data!B11/HAL_Data!B13 -> 0.26303526 | C8: =HAL_Data!C11/HAL_Data!C13 -> 0.24724249 | D8: =HAL_Data!D11/HAL_Data!D13 -> 0.26154849 | E8: =HAL_Data!E11/HAL_Data!E13 -> 0.23910123 | F8: =HAL_Data!F11/HAL_Data!F13 -> 0.22211934
A9: ROA | B9: =HAL_Data!B11/HAL_Data!B15 -> 0.084309755 | C9: =HAL_Data!C11/HAL_Data!C15 -> 0.084127259 | D9: =HAL_Data!D11/HAL_Data!D15 -> 0.094189912 | E9: =HAL_Data!E11/HAL_Data!E15 -> 0.076947138 | F9: =HAL_Data!F11/HAL_Data!F15 -> 0.068844164
A10: Net debt / EBITDA | B10: =(HAL_Data!B14-HAL_Data!B11)/HAL_Data!B6 -> -0.92908587 | C10: =(HAL_Data!C14-HAL_Data!C11)/HAL_Data!C6 -> -0.86389471 | D10: =(HAL_Data!D14-HAL_Data!D11)/HAL_Data!D6 -> -0.77635357 | E10: =(HAL_Data!E14-HAL_Data!E11)/HAL_Data!E6 -> -0.8640474 | F10: =(HAL_Data!F14-HAL_Data!F11)/HAL_Data!F6 -> -0.93193449
A12: Dassault (adjusted)
A13: Ratio | B13: 2021 | C13: 2022 | D13: 2023 | E13: 2024 | F13: 2025
A14: Net margin (reported) | B14: =Dassault_Data!B7/Dassault_Data!B5 -> 0.095797622 | C14: =Dassault_Data!C7/Dassault_Data!C5 -> 0.11976912 | D14: =Dassault_Data!D7/Dassault_Data!D5 -> 0.18439126 | E14: =Dassault_Data!E7/Dassault_Data!E5 -> 0.16999356 | F14: =Dassault_Data!F7/Dassault_Data!F5 -> 0.14291487
A15: Net margin (ex-Thales) | B15: =(Dassault_Data!B7-Dassault_Data!B8)/Dassault_Data!B5 -> 0.04935029 | C15: =(Dassault_Data!C7-Dassault_Data!C8)/Dassault_Data!C5 -> 0.064069264 | D15: =(Dassault_Data!D7-Dassault_Data!D8)/Dassault_Data!D5 -> 0.090738814 | E15: =(Dassault_Data!E7-Dassault_Data!E8)/Dassault_Data!E5 -> 0.088377334 | F15: =(Dassault_Data!F7-Dassault_Data!F8)/Dassault_Data!F5 -> 0.070985991
A16: Operating margin | B16: =Dassault_Data!B6/Dassault_Data!B5 -> 0.072850429 | C16: =Dassault_Data!C6/Dassault_Data!C5 -> 0.082539683 | D16: =Dassault_Data!D6/Dassault_Data!D5 -> 0.072632674 | E16: =Dassault_Data!E6/Dassault_Data!E5 -> 0.083547972 | F16: =Dassault_Data!F6/Dassault_Data!F5 -> 0.085533405
A17: Self-funded R&D % sales | B17: =Dassault_Data!B9/Dassault_Data!B5 -> 0.059441526 | C17: =Dassault_Data!C9/Dassault_Data!C5 -> 0.082539683 | D17: =Dassault_Data!D9/Dassault_Data!D5 -> 0.10052029 | E17: =Dassault_Data!E9/Dassault_Data!E5 -> 0.070347714 | F17: =Dassault_Data!F9/Dassault_Data!F5 -> 0.052397629
A19: Lockheed Martin
A20: Ratio | B20: 2021 | C20: 2022 | D20: 2023 | E20: 2024 | F20: 2025
A21: Net margin | B21: =Lockheed_Data!B8/Lockheed_Data!B5 -> 0.094191874 | C21: =Lockheed_Data!C8/Lockheed_Data!C5 -> 0.086869544 | D21: =Lockheed_Data!D8/Lockheed_Data!D5 -> 0.1024108 | E21: =Lockheed_Data!E8/Lockheed_Data!E5 -> 0.075109441 | F21: =Lockheed_Data!F8/Lockheed_Data!F5 -> 0.066850549
A22: Gross margin | B22: =Lockheed_Data!B6/Lockheed_Data!B5 -> 0.13515005 | C22: =Lockheed_Data!C6/Lockheed_Data!C5 -> 0.12559105 | D22: =Lockheed_Data!D6/Lockheed_Data!D5 -> 0.12548283 | E22: =Lockheed_Data!E6/Lockheed_Data!E5 -> 0.10724491 | F22: =Lockheed_Data!F6/Lockheed_Data!F5 -> 0.098257115
A23: EBIT margin | B23: =Lockheed_Data!B7/Lockheed_Data!B5 -> 0.13607482 | C23: =Lockheed_Data!C7/Lockheed_Data!C5 -> 0.12651552 | D23: =Lockheed_Data!D7/Lockheed_Data!D5 -> 0.1258972 | E23: =Lockheed_Data!E7/Lockheed_Data!E5 -> 0.098714863 | F23: =Lockheed_Data!F7/Lockheed_Data!F5 -> 0.098896706
A24: ROA | B24: =Lockheed_Data!B8/Lockheed_Data!B10 -> 0.12413264 | C24: =Lockheed_Data!C8/Lockheed_Data!C10 -> 0.10839637 | D24: =Lockheed_Data!D8/Lockheed_Data!D10 -> 0.13192009 | E24: =Lockheed_Data!E8/Lockheed_Data!E10 -> 0.099154511 | F24: =Lockheed_Data!F8/Lockheed_Data!F10 -> 0.091218182
A25: Net debt / EBITDA | B25: =Lockheed_Data!B11/(Lockheed_Data!B5*Lockheed_Data!B16) -> 0.76981166 | C25: =Lockheed_Data!C11/(Lockheed_Data!C5*Lockheed_Data!C16) -> 1.3209009 | D25: =Lockheed_Data!D11/(Lockheed_Data!D5*Lockheed_Data!D16) -> 1.6114178 | E25: =Lockheed_Data!E11/(Lockheed_Data!E5*Lockheed_Data!E16) -> 2.0743123 | F25: =Lockheed_Data!F11/(Lockheed_Data!F5*Lockheed_Data!F16) -> 1.8664283
A27: Revenue CAGR (5-yr) & latest-year comparison
A28: Metric (latest yr) | B28: HAL | C28: Dassault | D28: Lockheed
A29: Revenue CAGR | B29: =POWER(HAL_Data!F5/HAL_Data!B5,1/4)-1 -> 0.076710376 | C29: =POWER(Dassault_Data!F5/Dassault_Data!B5,1/4)-1 -> 0.0065025156 | D29: =POWER(Lockheed_Data!F5/Lockheed_Data!B5,1/4)-1 -> 0.02859593
A30: Net margin | B30: =HAL_Data!F11/HAL_Data!F5 -> 0.27549941 | C30: =Dassault_Data!F7/Dassault_Data!F5 -> 0.14291487 | D30: =Lockheed_Data!F8/Lockheed_Data!F5 -> 0.066850549
A31: Return on assets | B31: =HAL_Data!F11/HAL_Data!F15 -> 0.068844164 | C31: =0.09 -> 0.09 | D31: =Lockheed_Data!F8/Lockheed_Data!F10 -> 0.091218182

Sheet DuPont
A1: DuPont Decomposition of ROE (latest year)
A2: ROE = Net margin × Asset turnover × Equity multiplier. *Dassault assets/equity are approximate inputs.
A4: Company | B4: Net margin | C4: Asset turnover | D4: Equity multiplier | E4: ROE (= product) | G4: Assets | H4: Equity
A5: HAL | B5: =HAL_Data!F11/HAL_Data!F5 -> 0.27549941 | C5: =HAL_Data!F5/HAL_Data!F15 -> 0.24988861 | D5: =HAL_Data!F15/HAL_Data!F13 -> 3.2264077 | E5: =B5*C5*D5 -> 0.22211934 | G5: Dassault approx (€m):
A6: Dassault* | B6: =Dassault_Data!F7/Dassault_Data!F5 -> 0.14291487 | C6: =Dassault_Data!F5/G6 -> 0.35352381 | D6: =G6/H6 -> 4.7727273 | E6: =B6*C6*D6 -> 0.24113636 | G6: 21000 | H6: 4400
A7: Lockheed Martin | B7: =Lockheed_Data!F8/Lockheed_Data!F5 -> 0.066850549 | C7: =Lockheed_Data!F5/Lockheed_Data!F10 -> 1.3645091 | D7: =Lockheed_Data!F10/Lockheed_Data!F9 -> 8.2089552 | E7: =B7*C7*D7 -> 0.74880597
A9: Read: HAL & Dassault reach a similar ROE by different routes (HAL via margin); Lockheed's high ROE is mostly leverage (equity multiplier > 8×).

Sheet Scorecard
A1: Benchmarking Scorecard
A2: A = HAL clearly stronger → D = HAL clearly weaker, relative to that peer.
A4: Parameter | B4: HAL vs Dassault | C4: HAL vs Lockheed | D4: Comment
A5: Profitability (margins) | B5: A | C5: B | D5: HAL ahead; Dassault flattered by Thales
A6: Returns quality (ROA/ROCE) | B6: A | C6: B | D6: HAL high-quality; LMT ROE via leverage
A7: Liquidity / net cash | B7: A | C7: A | D7: HAL & Dassault net-cash; LMT levered
A8: Solvency / leverage | B8: A | C8: B | D8: HAL near debt-free
A9: Efficiency / working capital | B9: D | C9: C | D9: HAL's main weakness — inventory lock-up
A10: Revenue growth | B10: A | C10: B | D10: HAL fastest & steadiest
A11: Order-book visibility | B11: B | C11: A | D11: All strong; Dassault deepest cover
A12: R&D intensity (on-books) | B12: C | C12: D | D12: Misleading — much HAL R&D off-books
A13: IP / design authority | B13: C | C13: D | D13: Peers own platform IP
A14: Diversification | B14: D | C14: B | D14: HAL & Dassault concentrated; LMT broad
A15: Capital return to holders | B15: B | C15: A | D15: LMT & Dassault higher payout
A16: Valuation / growth premium | B16: A | C16: A | D16: Market already rewards HAL

Sheet Scenario_Tool
A1: ★ Interactive Scenario Tool
A2: Pick options from the yellow dropdowns. Outputs recalculate automatically.
A4: Step 1 — Working-capital improvement scenario: | D4: Base case
A5: Step 2 — Benchmark HAL against which peer: | D5: Dassault
A7: Scenario assumptions (editable):
A8: Scenario | B8: Inventory-day reduction
A9: Conservative | B9: 0.05
A10: Base case | B10: 0.1
A11: Aggressive | B11: 0.15
A13: Working-capital cash-release calculation
A14: Current inventory days (FY26) | D14: =HAL_Data!F16 -> 780
A15: Annual COGS / expenses (FY26, ₹cr) | D15: =HAL_Data!F12 -> 23319
A16: Selected reduction % | D16: =INDEX($B$9:$B$11,MATCH($D$4,$A$9:$A$11,0)) -> 0.1
A17: New inventory days | D17: =D14*(1-D16) -> 702
A18: Inventory days saved | D18: =D14-D17 -> 78
A19: Implied inventory value today (₹cr) | D19: =D14/365*D15 -> 49832.384
A20: ➤ CASH RELEASED (₹ crore) | D20: =D18/365*D15 -> 4983.2384
A21: (≈ cash freed in one year if the selected inventory-day reduction is achieved, holding COGS constant)
A24: HAL vs selected peer — latest year
A25: Metric | B25: HAL | C25: Selected peer
A26: Net margin | B26: =HAL_Data!F11/HAL_Data!F5 -> 0.27549941 | C26: =IF($D$5="Dassault",Dassault_Data!F7/Dassault_Data!F5,Lockheed_Data!F8/Lockheed_Data!F5) -> 0.14291487
A27: Revenue CAGR (5-yr) | B27: =POWER(HAL_Data!F5/HAL_Data!B5,1/4)-1 -> 0.076710376 | C27: =IF($D$5="Dassault",POWER(Dassault_Data!F5/Dassault_Data!B5,1/4)-1,POWER(Lockheed_Data!F5/Lockheed_Data!B5,1/4)-1) -> 0.0065025156
A28: Net debt / EBITDA | B28: =(HAL_Data!F14-HAL_Data!F11)/HAL_Data!F6 -> -0.93193449 | C28: =IF($D$5="Dassault",-2.5,Lockheed_Data!F11/(Lockheed_Data!F5*Lockheed_Data!F16)) -> -2.5
A30: Tip: change the dropdowns in D4 / D5 and press recalc (or just reopen) to see every figure update.

Sheet Charts
A1: Visual Trends
A2: Charts read directly from the Ratios sheet.
A4: Net margin (%) — pulled for charting
A5: Year | B5: HAL | C5: Dassault (rep.) | D5: Lockheed
A6: Y1 | B6: =HAL_Data!B11/HAL_Data!B5 -> 0.20633631 | C6: =Dassault_Data!B7/Dassault_Data!B5 -> 0.095797622 | D6: =Lockheed_Data!B8/Lockheed_Data!B5 -> 0.094191874
A7: Y2 | B7: =HAL_Data!C11/HAL_Data!C5 -> 0.21643703 | C7: =Dassault_Data!C7/Dassault_Data!C5 -> 0.11976912 | D7: =Lockheed_Data!C8/Lockheed_Data!C5 -> 0.086869544
A8: Y3 | B8: =HAL_Data!D11/HAL_Data!D5 -> 0.25084757 | C8: =Dassault_Data!D7/Dassault_Data!D5 -> 0.18439126 | D8: =Lockheed_Data!D8/Lockheed_Data!D5 -> 0.1024108
A9: Y4 | B9: =HAL_Data!E11/HAL_Data!E5 -> 0.26997192 | C9: =Dassault_Data!E7/Dassault_Data!E5 -> 0.16999356 | D9: =Lockheed_Data!E8/Lockheed_Data!E5 -> 0.075109441
A10: Y5 | B10: =HAL_Data!F11/HAL_Data!F5 -> 0.27549941 | C10: =Dassault_Data!F7/Dassault_Data!F5 -> 0.14291487 | D10: =Lockheed_Data!F8/Lockheed_Data!F5 -> 0.066850549
A13: Latest-year net margin
A14: Company | B14: Net margin
A15: HAL | B15: =HAL_Data!F11/HAL_Data!F5 -> 0.27549941
A16: Dassault | B16: =Dassault_Data!F7/Dassault_Data!F5 -> 0.14291487
A17: Lockheed | B17: =Lockheed_Data!F8/Lockheed_Data!F5 -> 0.066850549
